arbiter_engine/__init__.py
arbiter_engine/api.py
arbiter_engine/cli.py
arbiter_engine/core.py
arbiter_engine/local_engine.py
arbiter_engine/vectors.py
arbiter_engine/version.py
arbiter_engine-0.5.1.dist-info/licenses/LICENSE.txt
arbiter_engine-0.5.1.dist-info/METADATA
arbiter_engine-0.5.1.dist-info/WHEEL
arbiter_engine-0.5.1.dist-info/entry_points.txt
arbiter_engine-0.5.1.dist-info/top_level.txt
arbiter_engine-0.5.1.dist-info/RECORD
