Metadata-Version: 2.4
Name: arbiter-engine
Version: 0.5.1
Summary: Actual Intelligence. Semantic coherence engine. 72-dimensional disambiguation. 26MB. Deterministic.
Author-email: Joel David Trout II <founder@traut.ai>
License: TRAUT Applied Research Proprietary License
Project-URL: Homepage, https://getarbiter.dev
Project-URL: Documentation, https://api.arbiter.traut.ai/docs
Keywords: disambiguation,semantic,rag,vector-search,nlp,embeddings,coherence,reranking,polysemy,word-sense,semantic-search,deterministic,air-gapped,actual-intelligence
Classifier: Development Status :: 4 - Beta
Classifier: Intended Audience :: Developers
Classifier: Intended Audience :: Science/Research
Classifier: Topic :: Scientific/Engineering :: Artificial Intelligence
Classifier: Topic :: Text Processing :: Linguistic
Classifier: Programming Language :: Python :: 3
Classifier: Programming Language :: Python :: 3.8
Classifier: Programming Language :: Python :: 3.9
Classifier: Programming Language :: Python :: 3.10
Classifier: Programming Language :: Python :: 3.11
Classifier: Programming Language :: Python :: 3.12
Classifier: License :: Other/Proprietary License
Requires-Python: >=3.8
License-File: LICENSE.txt
Requires-Dist: requests>=2.25.0
Requires-Dist: numpy>=1.20.0
Requires-Dist: scipy>=1.7.0
Dynamic: license-file
